{"merchants": [{"businessNameAr": "Bilal Mosque", "businessName": "Bilal Mosque", "category": "mosque", "description": "خطبة الجمعة: 13:30، 14:30 | اللغة: عربية + ألمانية | سعة: -", "country": "ألمانيا", "city": "برلين", "address": "برلين", "phone": "", "website": ""}, {"businessNameAr": "DITIB Zentralmoschee Köln", "businessName": "DITIB Zentralmoschee Köln", "category": "mosque", "description": "خطبة الجمعة: - | اللغة: تركية + ألمانية | سعة: -", "country": "ألمانيا", "city": "كولونيا", "address": "Venloer Str. 160, 50823 Köln", "phone": "", "website": ""}, {"businessNameAr": "DITIB Central Mosque", "businessName": "DITIB Central Mosque", "category": "mosque", "description": "خطبة الجمعة: 12:30 | اللغة: تركية + ألمانية | سعة: 1000", "country": "ألمانيا", "city": "فرانكفورت", "address": "Münchener Str. 21, 60329 Frankfurt", "phone": "+49 69 2426600", "website": ""}, {"businessNameAr": "Abu Bakr Mosque", "businessName": "Abu Bakr Mosque", "category": "mosque", "description": "خطبة الجمعة: - | اللغة: تركية + ألمانية | سعة: -", "country": "ألمانيا", "city": "فرانكفورت", "address": "Praunheimer Landstraße 21, Frankfurt", "phone": "+49 69 7891211", "website": ""}, {"businessNameAr": "Pak Darul-Islam Mosque", "businessName": "Pak Darul-Islam Mosque", "category": "mosque", "description": "خطبة الجمعة: - | اللغة: أوردو + ألمانية | سعة: -", "country": "ألمانيا", "city": "فرانكفورت", "address": "Münchener Str. 55, 60329 Frankfurt", "phone": "+49 69 235688", "website": ""}, {"businessNameAr": "London Central Mosque", "businessName": "London Central Mosque", "category": "mosque", "description": "خطبة الجمعة: 13:00 | اللغة: عربية + إنجليزية | سعة: 5000", "country": "بريطانيا", "city": "لندن", "address": "146 Park Rd, London NW8 7RG", "phone": "", "website": ""}, {"businessNameAr": "East London Mosque", "businessName": "East London Mosque", "category": "mosque", "description": "خطبة الجمعة: - | اللغة: عربية + إنجليزية + بنغالية | سعة: 7000", "country": "بريطانيا", "city": "لندن", "address": "82-92 Whitechapel Rd, London E1 1JQ", "phone": "", "website": ""}, {"businessNameAr": "Birmingham Central Mosque", "businessName": "Birmingham Central Mosque", "category": "mosque", "description": "خطبة الجمعة: - | اللغة: إنجليزية | سعة: 6000", "country": "بريطانيا", "city": "برمنغهام", "address": "Highgate, Birmingham", "phone": "", "website": ""}, {"businessNameAr": "Essalam Mosque", "businessName": "Essalam Mosque", "category": "mosque", "description": "خطبة الجمعة: - | اللغة: عربية + هولندية | سعة: 3000", "country": "هولندا", "city": "روتردام", "address": "Vredesplein 7, 3074 SN Rotterdam", "phone": "+31 10 419 3666", "website": ""}, {"businessNameAr": "Mevlana Mosque", "businessName": "Mevlana Mosque", "category": "mosque", "description": "خطبة الجمعة: - | اللغة: تركية + هولندية | سعة: -", "country": "هولندا", "city": "روتردام", "address": "Mevlanaplein 1, 3022 EP Rotterdam", "phone": "+31 10 476 4107", "website": ""}, {"businessNameAr": "Great Mosque of Brussels", "businessName": "Great Mosque of Brussels", "category": "mosque", "description": "خطبة الجمعة: - | اللغة: عربية + فرنسية | سعة: -", "country": "بلجيكا", "city": "بروكسل", "address": "Parc du Cinquantenaire, Brussels", "phone": "", "website": ""}, {"businessNameAr": "Islamisches Zentrum Wien", "businessName": "Islamisches Zentrum Wien", "category": "mosque", "description": "خطبة الجمعة: 14:00 | اللغة: عربية + ألمانية | سعة: -", "country": "النمسا", "city": "فيينا", "address": "Am Bruckhaufen 3, 1210 Wien", "phone": "+43 1 293 3194", "website": ""}, {"businessNameAr": "Al-Hidaya Masjid", "businessName": "Al-Hidaya Masjid", "category": "mosque", "description": "خطبة الجمعة: - | اللغة: - | سعة: -", "country": "النمسا", "city": "فيينا", "address": "Praterstrasse 52, 1020 Wien", "phone": "+43 1 214 6291", "website": ""}, {"businessNameAr": "Kuba Mosque", "businessName": "Kuba Mosque", "category": "mosque", "description": "خطبة الجمعة: - | اللغة: - | سعة: -", "country": "النمسا", "city": "فيينا", "address": "Sebastian Kneipgasse 13/2, 1020 Wien", "phone": "+43 1 726 7033", "website": ""}, {"businessNameAr": "Ahmet Yesevi Mosque", "businessName": "Ahmet Yesevi Mosque", "category": "mosque", "description": "خطبة الجمعة: - | اللغة: تركية + ألمانية | سعة: -", "country": "النمسا", "city": "فيينا", "address": "Taborstrasse 108/3, 1020 Wien", "phone": "+43 1 212 4708", "website": ""}, {"businessNameAr": "Grand Mosque of Copenhagen", "businessName": "Grand Mosque of Copenhagen", "category": "mosque", "description": "خطبة الجمعة: - | اللغة: عربية + دنماركية | سعة: -", "country": "أوروبا", "city": "كوبنهاجن", "address": "Vingelodden 1, 2200 København N", "phone": "+45 70605545", "website": ""}, {"businessNameAr": "Imam Ali Mosque", "businessName": "Imam Ali Mosque", "category": "mosque", "description": "خطبة الجمعة: - | اللغة: عربية + دنماركية | سعة: -", "country": "أوروبا", "city": "كوبنهاجن", "address": "Vibevej 25, 3, Copenhagen", "phone": "+45 38100078", "website": ""}, {"businessNameAr": "Stockholm Mosque", "businessName": "Stockholm Mosque", "category": "mosque", "description": "خطبة الجمعة: - | اللغة: عربية + سويدية | سعة: -", "country": "السويد", "city": "ستوكهولم", "address": "ستوكهولم", "phone": "", "website": ""}, {"businessNameAr": "Masjid Omar Ben Khatab", "businessName": "Masjid Omar Ben Khatab", "category": "mosque", "description": "خطبة الجمعة: - | اللغة: عربية + سويدية | سعة: -", "country": "السويد", "city": "ستوكهولم", "address": "ستوكهولم", "phone": "", "website": ""}, {"businessNameAr": "Mosque of Rome", "businessName": "Mosque of Rome", "category": "mosque", "description": "خطبة الجمعة: - | اللغة: عربية + إيطالية | سعة: -", "country": "إيطاليا", "city": "روما", "address": "روما", "phone": "", "website": ""}, {"businessNameAr": "Via Padova area prayer room", "businessName": "Via Padova area prayer room", "category": "mosque", "description": "خطبة الجمعة: - | اللغة: عربية + إيطالية | سعة: -", "country": "إيطاليا", "city": "ميلانو", "address": "Via Padova area, Milan", "phone": "", "website": ""}, {"businessNameAr": "Lavapiés area prayer room", "businessName": "Lavapiés area prayer room", "category": "mosque", "description": "خطبة الجمعة: - | اللغة: عربية + إسبانية | سعة: -", "country": "إسبانيا", "city": "مدريد", "address": "Lavapiés, Madrid", "phone": "", "website": ""}, {"businessNameAr": "El Raval area prayer room", "businessName": "El Raval area prayer room", "category": "mosque", "description": "خطبة الجمعة: - | اللغة: عربية + إسبانية | سعة: -", "country": "إسبانيا", "city": "برشلونة", "address": "El Raval, Barcelona", "phone": "", "website": ""}, {"businessNameAr": "Athens area prayer room", "businessName": "Athens area prayer room", "category": "mosque", "description": "خطبة الجمعة: - | اللغة: عربية + إنجليزية | سعة: -", "country": "اليونان", "city": "أثينا", "address": "أثينا", "phone": "", "website": ""}]}